Metadata-Version: 2.1
Name: rpi-vidlooper
Version: 0.5
Summary: Raspberry Pi GPIO-controlled video looper
Home-page: UNKNOWN
Author: Alex Lubbock
Author-email: code@alexlubbock.com
License: UNKNOWN
Platform: UNKNOWN
License-File: LICENSE
